{
    "LVcustomers":[
        {
            "busId":4,
            "coded_ean":"SAG0125358071",
            "connectionCapacity":3.3,
            "deviceId":0,
            "device_profile_file":"Load profiles POLA/2020/profile_SAG0125358071_2020.csv",
            "exclusiveNight":false,
            "phases":[
                3
            ],
            "yearlyNetConsumption":1463.6629457596155,
            "yearlyNetReactiveConsumption":127.66819254380893
        },
        {
            "busId":4,
            "coded_ean":"SAG0125358321",
            "connectionCapacity":3.45,
            "deviceId":1,
            "device_profile_file":"Load profiles POLA/2020/profile_SAG0125358321_2020.csv",
            "exclusiveNight":false,
            "phases":[
                1
            ],
            "yearlyNetConsumption":1444.7643926672556,
            "yearlyNetReactiveConsumption":110.09539348051614
        },
        {
            "busId":4,
            "coded_ean":"SAG0125358322",
            "connectionCapacity":3.45,
            "deviceId":2,
            "device_profile_file":"Load profiles POLA/2020/profile_SAG0125358322_2020.csv",
            "exclusiveNight":false,
            "phases":[
                3
            ],
            "yearlyNetConsumption":2038.5367055310821,
            "yearlyNetReactiveConsumption":121.6717475038728
        },
        {
            "busId":4,
            "coded_ean":"SAG0125358323",
            "connectionCapacity":6.6,
            "deviceId":3,
            "device_profile_file":"Load profiles POLA/2020/profile_SAG0125358323_2020.csv",
            "exclusiveNight":false,
            "phases":[
                3
            ],
            "yearlyNetConsumption":1184.4164353573215,
            "yearlyNetReactiveConsumption":154.55347154774427
        },
        {
            "busId":4,
            "coded_ean":"SAG0125358324",
            "connectionCapacity":3.3,
            "deviceId":4,
            "device_profile_file":"Load profiles POLA/2020/profile_SAG0125358324_2020.csv",
            "exclusiveNight":false,
            "phases":[
                2
            ],
            "yearlyNetConsumption":1977.9160046751076,
            "yearlyNetReactiveConsumption":152.84794999247399
        },
        {
            "busId":4,
            "coded_ean":"SAG0125358325",
            "connectionCapacity":3.45,
            "deviceId":5,
            "device_profile_file":"Load profiles POLA/2020/profile_SAG0125358325_2020.csv",
            "exclusiveNight":false,
            "phases":[
                1
            ],
            "yearlyNetConsumption":1481.6038190690438,
            "yearlyNetReactiveConsumption":129.0424444191254
        },
        {
            "busId":4,
            "coded_ean":"SAG0125358326",
            "connectionCapacity":3.3,
            "deviceId":6,
            "device_profile_file":"Load profiles POLA/2020/profile_SAG0125358326_2020.csv",
            "exclusiveNight":false,
            "phases":[
                2
            ],
            "yearlyNetConsumption":1708.4001453823785,
            "yearlyNetReactiveConsumption":123.36032229095703
        },
        {
            "busId":4,
            "coded_ean":"SAG0125358327",
            "connectionCapacity":4.6,
            "deviceId":7,
            "device_profile_file":"Load profiles POLA/2020/profile_SAG0125358327_2020.csv",
            "exclusiveNight":false,
            "phases":[
                3
            ],
            "yearlyNetConsumption":1308.4338307882824,
            "yearlyNetReactiveConsumption":152.86275658265833
        },
        {
            "busId":4,
            "coded_ean":"SAG0125358328",
            "connectionCapacity":3.3,
            "deviceId":8,
            "device_profile_file":"Load profiles POLA/2020/profile_SAG0125358328_2020.csv",
            "exclusiveNight":false,
            "phases":[
                2
            ],
            "yearlyNetConsumption":1869.2176971096437,
            "yearlyNetReactiveConsumption":150.53204698323862
        },
        {
            "busId":4,
            "coded_ean":"SAG0125358330",
            "connectionCapacity":3.45,
            "deviceId":9,
            "device_profile_file":"Load profiles POLA/2020/profile_SAG0125358330_2020.csv",
            "exclusiveNight":false,
            "phases":[
                2
            ],
            "yearlyNetConsumption":1511.859789781404,
            "yearlyNetReactiveConsumption":135.71190496102625
        },
        {
            "busId":4,
            "coded_ean":"ZIV0034844981",
            "connectionCapacity":3.45,
            "deviceId":10,
            "device_profile_file":"Load profiles POLA/2020/profile_ZIV0034844981_2020.csv",
            "exclusiveNight":false,
            "phases":[
                1
            ],
            "yearlyNetConsumption":1534.8763260204835,
            "yearlyNetReactiveConsumption":186.52550068851906
        },
        {
            "busId":4,
            "coded_ean":"ZIV0036294549",
            "connectionCapacity":13.86,
            "deviceId":11,
            "device_profile_file":"Load profiles POLA/2020/profile_ZIV0036294549_2020.csv",
            "exclusiveNight":false,
            "phases":[
                1,
                2,
                3
            ],
            "yearlyNetConsumption":4861.552665141499,
            "yearlyNetReactiveConsumption":728.3672503107351
        },
        {
            "busId":4,
            "coded_ean":"ZIV0036294550",
            "connectionCapacity":6.6,
            "deviceId":12,
            "device_profile_file":"Load profiles POLA/2020/profile_ZIV0036294550_2020.csv",
            "exclusiveNight":false,
            "phases":[
                1,
                2,
                3
            ],
            "yearlyNetConsumption":5184.872751837925,
            "yearlyNetReactiveConsumption":574.616381334426
        },
        {
            "busId":4,
            "coded_ean":"ZIV0046923941",
            "connectionCapacity":4.4,
            "deviceId":13,
            "device_profile_file":"Load profiles POLA/2020/profile_ZIV0046923941_2020.csv",
            "exclusiveNight":false,
            "phases":[
                3
            ],
            "yearlyNetConsumption":1027.5435578967072,
            "yearlyNetReactiveConsumption":119.5964339435101
        },
        {
            "busId":6,
            "coded_ean":"SAG0125360410",
            "connectionCapacity":4.6,
            "deviceId":14,
            "device_profile_file":"Load profiles POLA/2020/profile_SAG0125360410_2020.csv",
            "exclusiveNight":false,
            "phases":[
                1
            ],
            "yearlyNetConsumption":1247.3997321450668,
            "yearlyNetReactiveConsumption":150.85515350532202
        },
        {
            "busId":6,
            "coded_ean":"ZIV0034685019",
            "connectionCapacity":4.6,
            "deviceId":15,
            "device_profile_file":"Load profiles POLA/2020/profile_ZIV0034685019_2020.csv",
            "exclusiveNight":false,
            "phases":[
                2
            ],
            "yearlyNetConsumption":1496.512847718036,
            "yearlyNetReactiveConsumption":178.8565248044911
        },
        {
            "busId":6,
            "coded_ean":"ZIV0034685065",
            "connectionCapacity":8.05,
            "deviceId":16,
            "device_profile_file":"Load profiles POLA/2020/profile_ZIV0034685065_2020.csv",
            "exclusiveNight":false,
            "phases":[
                1
            ],
            "yearlyNetConsumption":1757.68370205239,
            "yearlyNetReactiveConsumption":175.6007867249071
        },
        {
            "busId":6,
            "coded_ean":"ZIV0034842052",
            "connectionCapacity":3.45,
            "deviceId":17,
            "device_profile_file":"Load profiles POLA/2020/profile_ZIV0034842052_2020.csv",
            "exclusiveNight":false,
            "phases":[
                1
            ],
            "yearlyNetConsumption":1147.9122723656283,
            "yearlyNetReactiveConsumption":139.1211469502738
        },
        {
            "busId":6,
            "coded_ean":"ZIV0034842053",
            "connectionCapacity":4.6,
            "deviceId":18,
            "device_profile_file":"Load profiles POLA/2020/profile_ZIV0034842053_2020.csv",
            "exclusiveNight":false,
            "phases":[
                1
            ],
            "yearlyNetConsumption":1541.9263202880659,
            "yearlyNetReactiveConsumption":133.35522952642643
        },
        {
            "busId":6,
            "coded_ean":"ZIV0034842058",
            "connectionCapacity":4.6,
            "deviceId":19,
            "device_profile_file":"Load profiles POLA/2020/profile_ZIV0034842058_2020.csv",
            "exclusiveNight":false,
            "phases":[
                3
            ],
            "yearlyNetConsumption":1918.1162609151713,
            "yearlyNetReactiveConsumption":125.62614348022613
        },
        {
            "busId":6,
            "coded_ean":"ZIV0034842419",
            "connectionCapacity":2.3,
            "deviceId":20,
            "device_profile_file":"Load profiles POLA/2020/profile_ZIV0034842419_2020.csv",
            "exclusiveNight":false,
            "phases":[
                2
            ],
            "yearlyNetConsumption":1244.9408316851427,
            "yearlyNetReactiveConsumption":154.77314880350514
        },
        {
            "busId":6,
            "coded_ean":"ZIV0034842420",
            "connectionCapacity":3.3,
            "deviceId":21,
            "device_profile_file":"Load profiles POLA/2020/profile_ZIV0034842420_2020.csv",
            "exclusiveNight":false,
            "phases":[
                2
            ],
            "yearlyNetConsumption":1518.0112872775808,
            "yearlyNetReactiveConsumption":121.30481772994315
        },
        {
            "busId":6,
            "coded_ean":"ZIV0034842421",
            "connectionCapacity":3.45,
            "deviceId":22,
            "device_profile_file":"Load profiles POLA/2020/profile_ZIV0034842421_2020.csv",
            "exclusiveNight":false,
            "phases":[
                2
            ],
            "yearlyNetConsumption":1543.2361490181297,
            "yearlyNetReactiveConsumption":151.6640497827092
        },
        {
            "busId":6,
            "coded_ean":"ZIV0034842422",
            "connectionCapacity":3.3,
            "deviceId":23,
            "device_profile_file":"Load profiles POLA/2020/profile_ZIV0034842422_2020.csv",
            "exclusiveNight":false,
            "phases":[
                1
            ],
            "yearlyNetConsumption":1203.7459819156088,
            "yearlyNetReactiveConsumption":182.59627907522736
        },
        {
            "busId":6,
            "coded_ean":"ZIV0034842423",
            "connectionCapacity":3.45,
            "deviceId":24,
            "device_profile_file":"Load profiles POLA/2020/profile_ZIV0034842423_2020.csv",
            "exclusiveNight":false,
            "phases":[
                3
            ],
            "yearlyNetConsumption":1974.0355599421666,
            "yearlyNetReactiveConsumption":166.15938347300218
        },
        {
            "busId":6,
            "coded_ean":"ZIV0034842424",
            "connectionCapacity":3.3,
            "deviceId":25,
            "device_profile_file":"Load profiles POLA/2020/profile_ZIV0034842424_2020.csv",
            "exclusiveNight":false,
            "phases":[
                1
            ],
            "yearlyNetConsumption":1638.626453299444,
            "yearlyNetReactiveConsumption":169.93755235723813
        },
        {
            "busId":6,
            "coded_ean":"ZIV0034842425",
            "connectionCapacity":3.3,
            "deviceId":26,
            "device_profile_file":"Load profiles POLA/2020/profile_ZIV0034842425_2020.csv",
            "exclusiveNight":false,
            "phases":[
                1
            ],
            "yearlyNetConsumption":1696.9072518044723,
            "yearlyNetReactiveConsumption":139.5393807002415
        },
        {
            "busId":6,
            "coded_ean":"ZIV0034842426",
            "connectionCapacity":3.45,
            "deviceId":27,
            "device_profile_file":"Load profiles POLA/2020/profile_ZIV0034842426_2020.csv",
            "exclusiveNight":false,
            "phases":[
                1
            ],
            "yearlyNetConsumption":1858.1317212603485,
            "yearlyNetReactiveConsumption":177.21407183689556
        },
        {
            "busId":6,
            "coded_ean":"ZIV0034842427",
            "connectionCapacity":3.3,
            "deviceId":28,
            "device_profile_file":"Load profiles POLA/2020/profile_ZIV0034842427_2020.csv",
            "exclusiveNight":false,
            "phases":[
                3
            ],
            "yearlyNetConsumption":1368.3551480991391,
            "yearlyNetReactiveConsumption":133.46836372179592
        },
        {
            "busId":6,
            "coded_ean":"ZIV0036295898",
            "connectionCapacity":13.86,
            "deviceId":29,
            "device_profile_file":"Load profiles POLA/2020/profile_ZIV0036295898_2020.csv",
            "exclusiveNight":false,
            "phases":[
                1,
                2,
                3
            ],
            "yearlyNetConsumption":5075.6147695873515,
            "yearlyNetReactiveConsumption":467.55203231583323
        },
        {
            "busId":6,
            "coded_ean":"ZIV0036295899",
            "connectionCapacity":13.2,
            "deviceId":30,
            "device_profile_file":"Load profiles POLA/2020/profile_ZIV0036295899_2020.csv",
            "exclusiveNight":false,
            "phases":[
                1,
                2,
                3
            ],
            "yearlyNetConsumption":4659.729456805214,
            "yearlyNetReactiveConsumption":478.30463123651407
        },
        {
            "busId":6,
            "coded_ean":"ZIV0036295902",
            "connectionCapacity":8.8,
            "deviceId":31,
            "device_profile_file":"Load profiles POLA/2020/profile_ZIV0036295902_2020.csv",
            "exclusiveNight":false,
            "phases":[
                1,
                2,
                3
            ],
            "yearlyNetConsumption":4164.122527930395,
            "yearlyNetReactiveConsumption":462.34427489118593
        },
        {
            "busId":6,
            "coded_ean":"ZIV0036405245",
            "connectionCapacity":4.6,
            "deviceId":32,
            "device_profile_file":"Load profiles POLA/2020/profile_ZIV0036405245_2020.csv",
            "exclusiveNight":false,
            "phases":[
                2
            ],
            "yearlyNetConsumption":1411.053848867507,
            "yearlyNetReactiveConsumption":147.7404252375019
        },
        {
            "busId":6,
            "coded_ean":"ZIV0040637170",
            "connectionCapacity":29.6,
            "deviceId":33,
            "device_profile_file":"Load profiles POLA/2020/profile_ZIV0040637170_2020.csv",
            "exclusiveNight":false,
            "phases":[
                1,
                2,
                3
            ],
            "yearlyNetConsumption":5613.190449716514,
            "yearlyNetReactiveConsumption":494.7085959189832
        },
        {
            "busId":6,
            "coded_ean":"ZIV0046917245",
            "connectionCapacity":3.45,
            "deviceId":34,
            "device_profile_file":"Load profiles POLA/2020/profile_ZIV0046917245_2020.csv",
            "exclusiveNight":false,
            "phases":[
                3
            ],
            "yearlyNetConsumption":1473.0752644904192,
            "yearlyNetReactiveConsumption":130.9805876017397
        },
        {
            "busId":8,
            "coded_ean":"SAG0125358142",
            "connectionCapacity":3.3,
            "deviceId":35,
            "device_profile_file":"Load profiles POLA/2020/profile_SAG0125358142_2020.csv",
            "exclusiveNight":false,
            "phases":[
                1
            ],
            "yearlyNetConsumption":1470.953864092226,
            "yearlyNetReactiveConsumption":126.56878252258525
        },
        {
            "busId":8,
            "coded_ean":"SAG0125358491",
            "connectionCapacity":4.6,
            "deviceId":36,
            "device_profile_file":"Load profiles POLA/2020/profile_SAG0125358491_2020.csv",
            "exclusiveNight":false,
            "phases":[
                2
            ],
            "yearlyNetConsumption":1210.3061532084996,
            "yearlyNetReactiveConsumption":138.6239826317347
        },
        {
            "busId":8,
            "coded_ean":"SAG0125358492",
            "connectionCapacity":3.3,
            "deviceId":37,
            "device_profile_file":"Load profiles POLA/2020/profile_SAG0125358492_2020.csv",
            "exclusiveNight":false,
            "phases":[
                3
            ],
            "yearlyNetConsumption":1637.1473914242656,
            "yearlyNetReactiveConsumption":142.5929780280078
        },
        {
            "busId":8,
            "coded_ean":"SAG0125358493",
            "connectionCapacity":3.45,
            "deviceId":38,
            "device_profile_file":"Load profiles POLA/2020/profile_SAG0125358493_2020.csv",
            "exclusiveNight":false,
            "phases":[
                3
            ],
            "yearlyNetConsumption":1781.4230446964161,
            "yearlyNetReactiveConsumption":173.07708022690144
        },
        {
            "busId":8,
            "coded_ean":"SAG0125358494",
            "connectionCapacity":3.3,
            "deviceId":39,
            "device_profile_file":"Load profiles POLA/2020/profile_SAG0125358494_2020.csv",
            "exclusiveNight":false,
            "phases":[
                2
            ],
            "yearlyNetConsumption":1235.254798521813,
            "yearlyNetReactiveConsumption":175.66950319474356
        },
        {
            "busId":8,
            "coded_ean":"SAG0125358495",
            "connectionCapacity":3.3,
            "deviceId":40,
            "device_profile_file":"Load profiles POLA/2020/profile_SAG0125358495_2020.csv",
            "exclusiveNight":false,
            "phases":[
                3
            ],
            "yearlyNetConsumption":1734.637503736531,
            "yearlyNetReactiveConsumption":158.19125520746078
        },
        {
            "busId":8,
            "coded_ean":"SAG0125358496",
            "connectionCapacity":4.6,
            "deviceId":41,
            "device_profile_file":"Load profiles POLA/2020/profile_SAG0125358496_2020.csv",
            "exclusiveNight":false,
            "phases":[
                1
            ],
            "yearlyNetConsumption":1817.22568828959,
            "yearlyNetReactiveConsumption":185.0488796237866
        },
        {
            "busId":8,
            "coded_ean":"SAG0125358497",
            "connectionCapacity":3.3,
            "deviceId":42,
            "device_profile_file":"Load profiles POLA/2020/profile_SAG0125358497_2020.csv",
            "exclusiveNight":false,
            "phases":[
                3
            ],
            "yearlyNetConsumption":1369.5251180605942,
            "yearlyNetReactiveConsumption":169.19483816567495
        },
        {
            "busId":8,
            "coded_ean":"SAG0125358498",
            "connectionCapacity":3.3,
            "deviceId":43,
            "device_profile_file":"Load profiles POLA/2020/profile_SAG0125358498_2020.csv",
            "exclusiveNight":false,
            "phases":[
                1
            ],
            "yearlyNetConsumption":1213.886696572686,
            "yearlyNetReactiveConsumption":110.13187397421997
        },
        {
            "busId":8,
            "coded_ean":"SAG0125358499",
            "connectionCapacity":4.4,
            "deviceId":44,
            "device_profile_file":"Load profiles POLA/2020/profile_SAG0125358499_2020.csv",
            "exclusiveNight":false,
            "phases":[
                1
            ],
            "yearlyNetConsumption":1787.9653174017146,
            "yearlyNetReactiveConsumption":124.65566812929227
        },
        {
            "busId":8,
            "coded_ean":"SAG0125358500",
            "connectionCapacity":3.45,
            "deviceId":45,
            "device_profile_file":"Load profiles POLA/2020/profile_SAG0125358500_2020.csv",
            "exclusiveNight":false,
            "phases":[
                2
            ],
            "yearlyNetConsumption":2146.9019176605243,
            "yearlyNetReactiveConsumption":150.22205500821983
        },
        {
            "busId":8,
            "coded_ean":"SAG0125358591",
            "connectionCapacity":3.45,
            "deviceId":46,
            "device_profile_file":"Load profiles POLA/2020/profile_SAG0125358591_2020.csv",
            "exclusiveNight":false,
            "phases":[
                3
            ],
            "yearlyNetConsumption":1641.4137755783972,
            "yearlyNetReactiveConsumption":163.91457264362282
        },
        {
            "busId":8,
            "coded_ean":"SAG0125358592",
            "connectionCapacity":3.3,
            "deviceId":47,
            "device_profile_file":"Load profiles POLA/2020/profile_SAG0125358592_2020.csv",
            "exclusiveNight":false,
            "phases":[
                3
            ],
            "yearlyNetConsumption":1372.912196449974,
            "yearlyNetReactiveConsumption":168.79017348372784
        },
        {
            "busId":8,
            "coded_ean":"SAG0125358593",
            "connectionCapacity":9.2,
            "deviceId":48,
            "device_profile_file":"Load profiles POLA/2020/profile_SAG0125358593_2020.csv",
            "exclusiveNight":false,
            "phases":[
                1
            ],
            "yearlyNetConsumption":1663.0486287659871,
            "yearlyNetReactiveConsumption":153.8689924850948
        },
        {
            "busId":8,
            "coded_ean":"SAG0125358594",
            "connectionCapacity":3.3,
            "deviceId":49,
            "device_profile_file":"Load profiles POLA/2020/profile_SAG0125358594_2020.csv",
            "exclusiveNight":false,
            "phases":[
                2
            ],
            "yearlyNetConsumption":1675.2213759945248,
            "yearlyNetReactiveConsumption":161.5423921888771
        },
        {
            "busId":8,
            "coded_ean":"SAG0125358595",
            "connectionCapacity":4.6,
            "deviceId":50,
            "device_profile_file":"Load profiles POLA/2020/profile_SAG0125358595_2020.csv",
            "exclusiveNight":false,
            "phases":[
                3
            ],
            "yearlyNetConsumption":1681.8515875249848,
            "yearlyNetReactiveConsumption":132.82501757373763
        },
        {
            "busId":8,
            "coded_ean":"SAG0125358597",
            "connectionCapacity":8.05,
            "deviceId":51,
            "device_profile_file":"Load profiles POLA/2020/profile_SAG0125358597_2020.csv",
            "exclusiveNight":false,
            "phases":[
                2
            ],
            "yearlyNetConsumption":1727.3616349277263,
            "yearlyNetReactiveConsumption":159.70838243868144
        },
        {
            "busId":8,
            "coded_ean":"SAG0125358598",
            "connectionCapacity":4.4,
            "deviceId":52,
            "device_profile_file":"Load profiles POLA/2020/profile_SAG0125358598_2020.csv",
            "exclusiveNight":false,
            "phases":[
                3
            ],
            "yearlyNetConsumption":1538.9321844592175,
            "yearlyNetReactiveConsumption":152.5354103972191
        },
        {
            "busId":8,
            "coded_ean":"SAG0125358600",
            "connectionCapacity":4.4,
            "deviceId":53,
            "device_profile_file":"Load profiles POLA/2020/profile_SAG0125358600_2020.csv",
            "exclusiveNight":false,
            "phases":[
                2
            ],
            "yearlyNetConsumption":1153.7545960555408,
            "yearlyNetReactiveConsumption":211.5080325780983
        },
        {
            "busId":8,
            "coded_ean":"ZIV0036294551",
            "connectionCapacity":9.9,
            "deviceId":54,
            "device_profile_file":"Load profiles POLA/2020/profile_ZIV0036294551_2020.csv",
            "exclusiveNight":false,
            "phases":[
                1,
                2,
                3
            ],
            "yearlyNetConsumption":5615.300181123963,
            "yearlyNetReactiveConsumption":398.0505193905731
        },
        {
            "busId":8,
            "coded_ean":"ZIV0036295901",
            "connectionCapacity":10.3,
            "deviceId":55,
            "device_profile_file":"Load profiles POLA/2020/profile_ZIV0036295901_2020.csv",
            "exclusiveNight":false,
            "phases":[
                1,
                2,
                3
            ],
            "yearlyNetConsumption":6806.207426305649,
            "yearlyNetReactiveConsumption":345.3829305373015
        },
        {
            "busId":8,
            "coded_ean":"ZIV0046916803",
            "connectionCapacity":4.6,
            "deviceId":56,
            "device_profile_file":"Load profiles POLA/2020/profile_ZIV0046916803_2020.csv",
            "exclusiveNight":false,
            "phases":[
                3
            ],
            "yearlyNetConsumption":1124.4068360036383,
            "yearlyNetReactiveConsumption":112.50824609112429
        },
        {
            "busId":8,
            "coded_ean":"ZIV0046917250",
            "connectionCapacity":3.45,
            "deviceId":57,
            "device_profile_file":"Load profiles POLA/2020/profile_ZIV0046917250_2020.csv",
            "exclusiveNight":false,
            "phases":[
                2
            ],
            "yearlyNetConsumption":1304.450275611426,
            "yearlyNetReactiveConsumption":145.10280818264275
        },
        {
            "busId":11,
            "coded_ean":"ZIV0034813116",
            "connectionCapacity":9.2,
            "deviceId":58,
            "device_profile_file":"Load profiles POLA/2020/profile_ZIV0034813116_2020.csv",
            "exclusiveNight":false,
            "phases":[
                2
            ],
            "yearlyNetConsumption":1323.0187643067165,
            "yearlyNetReactiveConsumption":165.7161416118257
        },
        {
            "busId":11,
            "coded_ean":"ZIV0034813790",
            "connectionCapacity":4.6,
            "deviceId":59,
            "device_profile_file":"Load profiles POLA/2020/profile_ZIV0034813790_2020.csv",
            "exclusiveNight":false,
            "phases":[
                3
            ],
            "yearlyNetConsumption":1051.7152433055458,
            "yearlyNetReactiveConsumption":148.43105807112087
        },
        {
            "busId":11,
            "coded_ean":"ZIV0034813889",
            "connectionCapacity":2.2,
            "deviceId":60,
            "device_profile_file":"Load profiles POLA/2020/profile_ZIV0034813889_2020.csv",
            "exclusiveNight":false,
            "phases":[
                3
            ],
            "yearlyNetConsumption":1427.2084096715716,
            "yearlyNetReactiveConsumption":158.89488919793857
        },
        {
            "busId":11,
            "coded_ean":"ZIV0034813890",
            "connectionCapacity":4.6,
            "deviceId":61,
            "device_profile_file":"Load profiles POLA/2020/profile_ZIV0034813890_2020.csv",
            "exclusiveNight":false,
            "phases":[
                2
            ],
            "yearlyNetConsumption":1810.294483412425,
            "yearlyNetReactiveConsumption":138.45537575766113
        },
        {
            "busId":11,
            "coded_ean":"ZIV0034813891",
            "connectionCapacity":3.3,
            "deviceId":62,
            "device_profile_file":"Load profiles POLA/2020/profile_ZIV0034813891_2020.csv",
            "exclusiveNight":false,
            "phases":[
                2
            ],
            "yearlyNetConsumption":1235.7636692281737,
            "yearlyNetReactiveConsumption":103.71300257800377
        },
        {
            "busId":11,
            "coded_ean":"ZIV0034813893",
            "connectionCapacity":3.45,
            "deviceId":63,
            "device_profile_file":"Load profiles POLA/2020/profile_ZIV0034813893_2020.csv",
            "exclusiveNight":false,
            "phases":[
                1
            ],
            "yearlyNetConsumption":1589.085831293688,
            "yearlyNetReactiveConsumption":145.71497373409574
        },
        {
            "busId":11,
            "coded_ean":"ZIV0034813894",
            "connectionCapacity":4.6,
            "deviceId":64,
            "device_profile_file":"Load profiles POLA/2020/profile_ZIV0034813894_2020.csv",
            "exclusiveNight":false,
            "phases":[
                2
            ],
            "yearlyNetConsumption":1057.7156873149831,
            "yearlyNetReactiveConsumption":148.3765761090629
        },
        {
            "busId":11,
            "coded_ean":"ZIV0034813895",
            "connectionCapacity":3.45,
            "deviceId":65,
            "device_profile_file":"Load profiles POLA/2020/profile_ZIV0034813895_2020.csv",
            "exclusiveNight":false,
            "phases":[
                3
            ],
            "yearlyNetConsumption":1456.1306194641986,
            "yearlyNetReactiveConsumption":130.2564776173753
        },
        {
            "busId":11,
            "coded_ean":"ZIV0034813896",
            "connectionCapacity":3.3,
            "deviceId":66,
            "device_profile_file":"Load profiles POLA/2020/profile_ZIV0034813896_2020.csv",
            "exclusiveNight":false,
            "phases":[
                2
            ],
            "yearlyNetConsumption":1357.319944748007,
            "yearlyNetReactiveConsumption":162.3872252664211
        },
        {
            "busId":11,
            "coded_ean":"ZIV0034813897",
            "connectionCapacity":3.3,
            "deviceId":67,
            "device_profile_file":"Load profiles POLA/2020/profile_ZIV0034813897_2020.csv",
            "exclusiveNight":false,
            "phases":[
                3
            ],
            "yearlyNetConsumption":1427.9430227931896,
            "yearlyNetReactiveConsumption":144.27357921852726
        },
        {
            "busId":11,
            "coded_ean":"ZIV0036309611",
            "connectionCapacity":5.9,
            "deviceId":68,
            "device_profile_file":"Load profiles POLA/2020/profile_ZIV0036309611_2020.csv",
            "exclusiveNight":false,
            "phases":[
                1,
                2,
                3
            ],
            "yearlyNetConsumption":4525.506603753824,
            "yearlyNetReactiveConsumption":539.656556285521
        },
        {
            "busId":11,
            "coded_ean":"ZIV0040343741",
            "connectionCapacity":4.6,
            "deviceId":69,
            "device_profile_file":"Load profiles POLA/2020/profile_ZIV0040343741_2020.csv",
            "exclusiveNight":false,
            "phases":[
                3
            ],
            "yearlyNetConsumption":1759.8559650009101,
            "yearlyNetReactiveConsumption":120.16925993604222
        },
        {
            "busId":11,
            "coded_ean":"ZIV0040430508",
            "connectionCapacity":9.9,
            "deviceId":70,
            "device_profile_file":"Load profiles POLA/2020/profile_ZIV0040430508_2020.csv",
            "exclusiveNight":false,
            "phases":[
                2
            ],
            "yearlyNetConsumption":1137.7963928221998,
            "yearlyNetReactiveConsumption":183.6972470505931
        },
        {
            "busId":11,
            "coded_ean":"ZIV0040430509",
            "connectionCapacity":3.45,
            "deviceId":71,
            "device_profile_file":"Load profiles POLA/2020/profile_ZIV0040430509_2020.csv",
            "exclusiveNight":false,
            "phases":[
                1
            ],
            "yearlyNetConsumption":1569.686779416872,
            "yearlyNetReactiveConsumption":183.48663168801576
        },
        {
            "busId":11,
            "coded_ean":"ZIV0040430627",
            "connectionCapacity":5.9,
            "deviceId":72,
            "device_profile_file":"Load profiles POLA/2020/profile_ZIV0040430627_2020.csv",
            "exclusiveNight":false,
            "phases":[
                3
            ],
            "yearlyNetConsumption":1451.1492873496752,
            "yearlyNetReactiveConsumption":156.2014692218477
        },
        {
            "busId":11,
            "coded_ean":"ZIV0040637191",
            "connectionCapacity":24.25,
            "deviceId":73,
            "device_profile_file":"Load profiles POLA/2020/profile_ZIV0040637191_2020.csv",
            "exclusiveNight":false,
            "phases":[
                1,
                2,
                3
            ],
            "yearlyNetConsumption":4056.4763115488417,
            "yearlyNetReactiveConsumption":438.4269444482529
        },
        {
            "busId":11,
            "coded_ean":"ZIV0046921834",
            "connectionCapacity":6.9,
            "deviceId":74,
            "device_profile_file":"Load profiles POLA/2020/profile_ZIV0046921834_2020.csv",
            "exclusiveNight":false,
            "phases":[
                3
            ],
            "yearlyNetConsumption":1658.4582080881041,
            "yearlyNetReactiveConsumption":129.51873181520259
        },
        {
            "busId":11,
            "coded_ean":"ZIV0046921835",
            "connectionCapacity":9.2,
            "deviceId":75,
            "device_profile_file":"Load profiles POLA/2020/profile_ZIV0046921835_2020.csv",
            "exclusiveNight":false,
            "phases":[
                3
            ],
            "yearlyNetConsumption":1461.3403948047808,
            "yearlyNetReactiveConsumption":180.40574335465644
        },
        {
            "busId":16,
            "coded_ean":"ZIV0034795299",
            "connectionCapacity":4.9,
            "deviceId":76,
            "device_profile_file":"Load profiles POLA/2020/profile_ZIV0034795299_2020.csv",
            "exclusiveNight":false,
            "phases":[
                2
            ],
            "yearlyNetConsumption":1277.263991933371,
            "yearlyNetReactiveConsumption":177.41671636386488
        },
        {
            "busId":19,
            "coded_ean":"ZIV0034795545",
            "connectionCapacity":5.5,
            "deviceId":77,
            "device_profile_file":"Load profiles POLA/2020/profile_ZIV0034795545_2020.csv",
            "exclusiveNight":false,
            "phases":[
                2
            ],
            "yearlyNetConsumption":1262.9373967309962,
            "yearlyNetReactiveConsumption":148.19696247823035
        },
        {
            "busId":23,
            "coded_ean":"ZIV0034813803",
            "connectionCapacity":4.4,
            "deviceId":78,
            "device_profile_file":"Load profiles POLA/2020/profile_ZIV0034813803_2020.csv",
            "exclusiveNight":false,
            "phases":[
                2
            ],
            "yearlyNetConsumption":1597.5961297506458,
            "yearlyNetReactiveConsumption":171.33928750225607
        },
        {
            "busId":26,
            "coded_ean":"ZIV0034813804",
            "connectionCapacity":3.3,
            "deviceId":79,
            "device_profile_file":"Load profiles POLA/2020/profile_ZIV0034813804_2020.csv",
            "exclusiveNight":false,
            "phases":[
                1
            ],
            "yearlyNetConsumption":1349.482819691747,
            "yearlyNetReactiveConsumption":181.7716154861804
        },
        {
            "busId":29,
            "coded_ean":"ZIV0034861801",
            "connectionCapacity":3.3,
            "deviceId":80,
            "device_profile_file":"Load profiles POLA/2020/profile_ZIV0034861801_2020.csv",
            "exclusiveNight":false,
            "phases":[
                1
            ],
            "yearlyNetConsumption":1479.3395648042215,
            "yearlyNetReactiveConsumption":160.30361832520566
        },
        {
            "busId":31,
            "coded_ean":"ZIV0034861799",
            "connectionCapacity":4.4,
            "deviceId":81,
            "device_profile_file":"Load profiles POLA/2020/profile_ZIV0034861799_2020.csv",
            "exclusiveNight":false,
            "phases":[
                2
            ],
            "yearlyNetConsumption":1436.0002838222008,
            "yearlyNetReactiveConsumption":161.07303295701973
        },
        {
            "busId":34,
            "coded_ean":"ZIV0034813798",
            "connectionCapacity":3.3,
            "deviceId":82,
            "device_profile_file":"Load profiles POLA/2020/profile_ZIV0034813798_2020.csv",
            "exclusiveNight":false,
            "phases":[
                1
            ],
            "yearlyNetConsumption":1718.5782113399057,
            "yearlyNetReactiveConsumption":109.82280517719514
        },
        {
            "busId":36,
            "coded_ean":"ZIV0034795538",
            "connectionCapacity":3.3,
            "deviceId":83,
            "device_profile_file":"Load profiles POLA/2020/profile_ZIV0034795538_2020.csv",
            "exclusiveNight":false,
            "phases":[
                2
            ],
            "yearlyNetConsumption":1547.101538556001,
            "yearlyNetReactiveConsumption":178.15616757342275
        },
        {
            "busId":42,
            "coded_ean":"SAG0125360052",
            "connectionCapacity":4.4,
            "deviceId":84,
            "device_profile_file":"Load profiles POLA/2020/profile_SAG0125360052_2020.csv",
            "exclusiveNight":false,
            "phases":[
                1
            ],
            "yearlyNetConsumption":1529.475323570417,
            "yearlyNetReactiveConsumption":102.77000514504562
        }
    ],
    "solarGens":[]
}