{
    "LVcustomers":[
        {
            "busId":6,
            "coded_ean":"ZIV0036310937",
            "connectionCapacity":10.39,
            "deviceId":0,
            "device_profile_file":"Load profiles POLA/2020/profile_ZIV0036310937_2020.csv",
            "exclusiveNight":false,
            "phases":[
                1,
                2,
                3
            ],
            "yearlyNetConsumption":3412.787947618429,
            "yearlyNetReactiveConsumption":430.6921086986746
        },
        {
            "busId":6,
            "coded_ean":"ZIV0042302732",
            "connectionCapacity":13.2,
            "deviceId":1,
            "device_profile_file":"Load profiles POLA/2020/profile_ZIV0042302732_2020.csv",
            "exclusiveNight":false,
            "phases":[
                1,
                2,
                3
            ],
            "yearlyNetConsumption":4986.515578732662,
            "yearlyNetReactiveConsumption":532.4715135513338
        },
        {
            "busId":6,
            "coded_ean":"ZIV0046916833",
            "connectionCapacity":4.6,
            "deviceId":2,
            "device_profile_file":"Load profiles POLA/2020/profile_ZIV0046916833_2020.csv",
            "exclusiveNight":false,
            "phases":[
                1
            ],
            "yearlyNetConsumption":1378.7719738474445,
            "yearlyNetReactiveConsumption":160.95503793111698
        },
        {
            "busId":6,
            "coded_ean":"ZIV0046916834",
            "connectionCapacity":2.3,
            "deviceId":3,
            "device_profile_file":"Load profiles POLA/2020/profile_ZIV0046916834_2020.csv",
            "exclusiveNight":false,
            "phases":[
                2
            ],
            "yearlyNetConsumption":1576.87350970597,
            "yearlyNetReactiveConsumption":124.88619331471571
        },
        {
            "busId":6,
            "coded_ean":"ZIV0046916836",
            "connectionCapacity":3.45,
            "deviceId":4,
            "device_profile_file":"Load profiles POLA/2020/profile_ZIV0046916836_2020.csv",
            "exclusiveNight":false,
            "phases":[
                1
            ],
            "yearlyNetConsumption":1641.4898014896355,
            "yearlyNetReactiveConsumption":141.4417262125521
        },
        {
            "busId":6,
            "coded_ean":"ZIV0046916837",
            "connectionCapacity":4.6,
            "deviceId":5,
            "device_profile_file":"Load profiles POLA/2020/profile_ZIV0046916837_2020.csv",
            "exclusiveNight":false,
            "phases":[
                1
            ],
            "yearlyNetConsumption":1670.3406521662491,
            "yearlyNetReactiveConsumption":186.86854515753615
        },
        {
            "busId":6,
            "coded_ean":"ZIV0046916838",
            "connectionCapacity":4.6,
            "deviceId":6,
            "device_profile_file":"Load profiles POLA/2020/profile_ZIV0046916838_2020.csv",
            "exclusiveNight":false,
            "phases":[
                1
            ],
            "yearlyNetConsumption":1192.4976150744226,
            "yearlyNetReactiveConsumption":191.44504828421807
        },
        {
            "busId":6,
            "coded_ean":"ZIV0046916839",
            "connectionCapacity":4.6,
            "deviceId":7,
            "device_profile_file":"Load profiles POLA/2020/profile_ZIV0046916839_2020.csv",
            "exclusiveNight":false,
            "phases":[
                3
            ],
            "yearlyNetConsumption":2179.5874591466472,
            "yearlyNetReactiveConsumption":154.27149406242577
        },
        {
            "busId":6,
            "coded_ean":"ZIV0046916841",
            "connectionCapacity":3.45,
            "deviceId":8,
            "device_profile_file":"Load profiles POLA/2020/profile_ZIV0046916841_2020.csv",
            "exclusiveNight":false,
            "phases":[
                3
            ],
            "yearlyNetConsumption":1659.1430830897314,
            "yearlyNetReactiveConsumption":158.85374775058742
        },
        {
            "busId":6,
            "coded_ean":"ZIV0046916842",
            "connectionCapacity":4.4,
            "deviceId":9,
            "device_profile_file":"Load profiles POLA/2020/profile_ZIV0046916842_2020.csv",
            "exclusiveNight":false,
            "phases":[
                3
            ],
            "yearlyNetConsumption":1579.1526156423722,
            "yearlyNetReactiveConsumption":140.10659391603093
        },
        {
            "busId":8,
            "coded_ean":"SAG0125356600",
            "connectionCapacity":4.4,
            "deviceId":10,
            "device_profile_file":"Load profiles POLA/2020/profile_SAG0125356600_2020.csv",
            "exclusiveNight":false,
            "phases":[
                2
            ],
            "yearlyNetConsumption":1366.6790488732213,
            "yearlyNetReactiveConsumption":135.04553660236706
        },
        {
            "busId":8,
            "coded_ean":"SAG0155286769",
            "connectionCapacity":4.4,
            "deviceId":11,
            "device_profile_file":"Load profiles POLA/2020/profile_SAG0155286769_2020.csv",
            "exclusiveNight":false,
            "phases":[
                3
            ],
            "yearlyNetConsumption":1587.3494602105059,
            "yearlyNetReactiveConsumption":167.15182091693484
        },
        {
            "busId":8,
            "coded_ean":"ZIV0034820608",
            "connectionCapacity":4.6,
            "deviceId":12,
            "device_profile_file":"Load profiles POLA/2020/profile_ZIV0034820608_2020.csv",
            "exclusiveNight":false,
            "phases":[
                2
            ],
            "yearlyNetConsumption":1363.6371625039258,
            "yearlyNetReactiveConsumption":221.67924709330947
        },
        {
            "busId":8,
            "coded_ean":"ZIV0034820609",
            "connectionCapacity":2.2,
            "deviceId":13,
            "device_profile_file":"Load profiles POLA/2020/profile_ZIV0034820609_2020.csv",
            "exclusiveNight":false,
            "phases":[
                3
            ],
            "yearlyNetConsumption":1367.3094000917474,
            "yearlyNetReactiveConsumption":137.77802047582313
        },
        {
            "busId":8,
            "coded_ean":"ZIV0034820612",
            "connectionCapacity":4.4,
            "deviceId":14,
            "device_profile_file":"Load profiles POLA/2020/profile_ZIV0034820612_2020.csv",
            "exclusiveNight":false,
            "phases":[
                1
            ],
            "yearlyNetConsumption":1769.9616675811608,
            "yearlyNetReactiveConsumption":112.03049785523893
        },
        {
            "busId":8,
            "coded_ean":"ZIV0034820613",
            "connectionCapacity":4.4,
            "deviceId":15,
            "device_profile_file":"Load profiles POLA/2020/profile_ZIV0034820613_2020.csv",
            "exclusiveNight":false,
            "phases":[
                2
            ],
            "yearlyNetConsumption":1465.7051971774617,
            "yearlyNetReactiveConsumption":103.37998244018362
        },
        {
            "busId":8,
            "coded_ean":"ZIV0034859223",
            "connectionCapacity":4.6,
            "deviceId":16,
            "device_profile_file":"Load profiles POLA/2020/profile_ZIV0034859223_2020.csv",
            "exclusiveNight":false,
            "phases":[
                2
            ],
            "yearlyNetConsumption":1117.8935303469475,
            "yearlyNetReactiveConsumption":132.58598414274599
        },
        {
            "busId":8,
            "coded_ean":"ZIV0034859227",
            "connectionCapacity":4.4,
            "deviceId":17,
            "device_profile_file":"Load profiles POLA/2020/profile_ZIV0034859227_2020.csv",
            "exclusiveNight":false,
            "phases":[
                3
            ],
            "yearlyNetConsumption":1283.1856751377047,
            "yearlyNetReactiveConsumption":143.55880329977995
        },
        {
            "busId":8,
            "coded_ean":"ZIV0036292196",
            "connectionCapacity":9.9,
            "deviceId":18,
            "device_profile_file":"Load profiles POLA/2020/profile_ZIV0036292196_2020.csv",
            "exclusiveNight":false,
            "phases":[
                1,
                2,
                3
            ],
            "yearlyNetConsumption":5707.5405863251,
            "yearlyNetReactiveConsumption":458.2455535033816
        },
        {
            "busId":8,
            "coded_ean":"ZIV0040335271",
            "connectionCapacity":2.3,
            "deviceId":19,
            "device_profile_file":"Load profiles POLA/2020/profile_ZIV0040335271_2020.csv",
            "exclusiveNight":false,
            "phases":[
                3
            ],
            "yearlyNetConsumption":1747.6752559325485,
            "yearlyNetReactiveConsumption":114.61846952214934
        },
        {
            "busId":8,
            "coded_ean":"ZIV0040335272",
            "connectionCapacity":4.4,
            "deviceId":20,
            "device_profile_file":"Load profiles POLA/2020/profile_ZIV0040335272_2020.csv",
            "exclusiveNight":false,
            "phases":[
                2
            ],
            "yearlyNetConsumption":1551.2452429977589,
            "yearlyNetReactiveConsumption":173.65988114084834
        },
        {
            "busId":8,
            "coded_ean":"ZIV0040335274",
            "connectionCapacity":4.6,
            "deviceId":21,
            "device_profile_file":"Load profiles POLA/2020/profile_ZIV0040335274_2020.csv",
            "exclusiveNight":false,
            "phases":[
                1
            ],
            "yearlyNetConsumption":1096.902504557505,
            "yearlyNetReactiveConsumption":153.55806565756328
        },
        {
            "busId":8,
            "coded_ean":"ZIV0042302740",
            "connectionCapacity":6.6,
            "deviceId":22,
            "device_profile_file":"Load profiles POLA/2020/profile_ZIV0042302740_2020.csv",
            "exclusiveNight":false,
            "phases":[
                1,
                2,
                3
            ],
            "yearlyNetConsumption":4240.76978751267,
            "yearlyNetReactiveConsumption":593.4251548699517
        },
        {
            "busId":8,
            "coded_ean":"ZIV0046917053",
            "connectionCapacity":3.45,
            "deviceId":23,
            "device_profile_file":"Load profiles POLA/2020/profile_ZIV0046917053_2020.csv",
            "exclusiveNight":false,
            "phases":[
                2
            ],
            "yearlyNetConsumption":1813.8436605517888,
            "yearlyNetReactiveConsumption":132.95840971294635
        },
        {
            "busId":8,
            "coded_ean":"ZIV0046917054",
            "connectionCapacity":4.6,
            "deviceId":24,
            "device_profile_file":"Load profiles POLA/2020/profile_ZIV0046917054_2020.csv",
            "exclusiveNight":false,
            "phases":[
                1
            ],
            "yearlyNetConsumption":1564.0482650694946,
            "yearlyNetReactiveConsumption":172.63234901633348
        },
        {
            "busId":8,
            "coded_ean":"ZIV0046917055",
            "connectionCapacity":4.6,
            "deviceId":25,
            "device_profile_file":"Load profiles POLA/2020/profile_ZIV0046917055_2020.csv",
            "exclusiveNight":false,
            "phases":[
                1
            ],
            "yearlyNetConsumption":1401.7443926645465,
            "yearlyNetReactiveConsumption":185.1642151669265
        },
        {
            "busId":8,
            "coded_ean":"ZIV0046917058",
            "connectionCapacity":4.6,
            "deviceId":26,
            "device_profile_file":"Load profiles POLA/2020/profile_ZIV0046917058_2020.csv",
            "exclusiveNight":false,
            "phases":[
                2
            ],
            "yearlyNetConsumption":1366.980938984074,
            "yearlyNetReactiveConsumption":136.94019196096048
        },
        {
            "busId":8,
            "coded_ean":"ZIV0046917059",
            "connectionCapacity":4.4,
            "deviceId":27,
            "device_profile_file":"Load profiles POLA/2020/profile_ZIV0046917059_2020.csv",
            "exclusiveNight":false,
            "phases":[
                1
            ],
            "yearlyNetConsumption":1483.8553618298904,
            "yearlyNetReactiveConsumption":74.77691481317567
        },
        {
            "busId":10,
            "coded_ean":"ZIV0034935804",
            "connectionCapacity":3.45,
            "deviceId":28,
            "device_profile_file":"Load profiles POLA/2020/profile_ZIV0034935804_2020.csv",
            "exclusiveNight":false,
            "phases":[
                2
            ],
            "yearlyNetConsumption":1504.6996544967778,
            "yearlyNetReactiveConsumption":164.14692792294034
        }
    ],
    "solarGens":[]
}